django_sneak_peek-0.0.1.dist-info/DESCRIPTION.rst
django_sneak_peek-0.0.1.dist-info/METADATA
django_sneak_peek-0.0.1.dist-info/metadata.json
django_sneak_peek-0.0.1.dist-info/RECORD
django_sneak_peek-0.0.1.dist-info/top_level.txt
django_sneak_peek-0.0.1.dist-info/WHEEL
sneak_peek_tag/__init__.py
sneak_peek_tag/models.py
sneak_peek_tag/migrations/0001_add_permission_sneak_peek.py
sneak_peek_tag/migrations/__init__.py
sneak_peek_tag/static/sneak_peek_tag/css/django-sneak-peek.css
sneak_peek_tag/static/sneak_peek_tag/images/django-sneak-peek-under-construction-border-image.png
sneak_peek_tag/templatetags/__init__.py
sneak_peek_tag/templatetags/sneak_peek.py
