Metadata-Version: 2.0
Name: django-sneak-peek
Version: 0.0.1
Summary: Django template tag to hide pre-release features in a template
Home-page: https://github.com/teddywing/django-sneak-peek
Author: Teddy Wing
Author-email: pypi@teddywing.com
License: MIT
Platform: UNKNOWN
Classifier: Development Status :: 4 - Beta
Classifier: Framework :: Django
Classifier: Intended Audience :: Developers
Classifier: License :: OSI Approved :: MIT License
Classifier: Natural Language :: English
Classifier: Operating System :: OS Independent
Classifier: Programming Language :: Python
Classifier: Programming Language :: Python :: 2
Requires-Dist: Django (>=1.4)
Requires-Dist: South
